{
	"name": "level 2",
	"background": "starfield",
	"balls": [{
		"size": 2,
		"velocity": 200
	},{
		"size": 1,
		"velocity": -300
	}],
	"player": {
		"position": {
			"x": 400,
			"y": 150
		}
	},
	"platforms": [{
			"type": "roof",
			"position": {
				"x": 0,
				"y": 568
			},
			"width": 100,
			"height": 32
		}, {
			"type": "ice",
			"position": {
				"x": 100,
				"y": 568
			},
			"width": 600,
			"height": 32
		}, {
			"type": "roof",
			"position": {
				"x": 700,
				"y": 568
			},
			"width": 100,
			"height": 32
		}
	]
}